{
	"actorsInfo": [
		{
			"transform":
			{
				"rotation":
				{
					"x": 0,
					"y": 0,
					"z": 0,
					"w": 1
				},
				"translation":
				{
					"x": 365,
					"y": 250.8165283203125,
					"z": 73.400733947753906
				},
				"scale3D":
				{
					"x": 1,
					"y": 1,
					"z": 1
				}
			},
			"assetPath": "SM_Ball_01"
		},
		{
			"transform":
			{
				"rotation":
				{
					"x": 0,
					"y": 0,
					"z": 0,
					"w": 1
				},
				"translation":
				{
					"x": -280,
					"y": -30,
					"z": 25
				},
				"scale3D":
				{
					"x": 1,
					"y": 1,
					"z": 1
				}
			},
			"assetPath": "SM_Cube_01"
		},
		{
			"transform":
			{
				"rotation":
				{
					"x": 0,
					"y": 0,
					"z": 0,
					"w": 1
				},
				"translation":
				{
					"x": -305,
					"y": 200,
					"z": 50
				},
				"scale3D":
				{
					"x": 1,
					"y": 1,
					"z": 1
				}
			},
			"assetPath": "SM_Cube_02"
		},
		{
			"transform":
			{
				"rotation":
				{
					"x": 0,
					"y": 0,
					"z": 0,
					"w": 1
				},
				"translation":
				{
					"x": -280,
					"y": -220,
					"z": 25
				},
				"scale3D":
				{
					"x": 1,
					"y": 1,
					"z": 1
				}
			},
			"assetPath": "SM_Cube_01"
		},
		{
			"transform":
			{
				"rotation":
				{
					"x": 0,
					"y": 0,
					"z": 0,
					"w": 1
				},
				"translation":
				{
					"x": 305,
					"y": -60,
					"z": 100
				},
				"scale3D":
				{
					"x": 1,
					"y": 1,
					"z": 1
				}
			},
			"assetPath": "SM_Cube_03"
		},
		{
			"transform":
			{
				"rotation":
				{
					"x": 0,
					"y": 0,
					"z": 0,
					"w": 1
				},
				"translation":
				{
					"x": 305,
					"y": -190,
					"z": 100
				},
				"scale3D":
				{
					"x": 1,
					"y": 1,
					"z": 1
				}
			},
			"assetPath": "SM_Cube_03"
		},
		{
			"transform":
			{
				"rotation":
				{
					"x": 0,
					"y": 0,
					"z": 0,
					"w": 1
				},
				"translation":
				{
					"x": -280,
					"y": -125,
					"z": 25
				},
				"scale3D":
				{
					"x": 1,
					"y": 1,
					"z": 1
				}
			},
			"assetPath": "SM_Cube_01"
		},
		{
			"transform":
			{
				"rotation":
				{
					"x": 0,
					"y": 0,
					"z": 0,
					"w": 1
				},
				"translation":
				{
					"x": -125,
					"y": 275,
					"z": 100
				},
				"scale3D":
				{
					"x": 1,
					"y": 1,
					"z": 1
				}
			},
			"assetPath": "SM_Cube_03"
		},
		{
			"transform":
			{
				"rotation":
				{
					"x": 0,
					"y": 0,
					"z": 0,
					"w": 1
				},
				"translation":
				{
					"x": 75,
					"y": 275,
					"z": 100
				},
				"scale3D":
				{
					"x": 1,
					"y": 1,
					"z": 1
				}
			},
			"assetPath": "SM_Cube_03"
		},
		{
			"transform":
			{
				"rotation":
				{
					"x": 0,
					"y": 0,
					"z": 0,
					"w": 1
				},
				"translation":
				{
					"x": 55,
					"y": -305,
					"z": 50
				},
				"scale3D":
				{
					"x": 1,
					"y": 1,
					"z": 1
				}
			},
			"assetPath": "SM_Cube_02"
		},
		{
			"transform":
			{
				"rotation":
				{
					"x": 0,
					"y": -0,
					"z": 0.25881916284561157,
					"w": 0.96592581272125244
				},
				"translation":
				{
					"x": -295,
					"y": 195,
					"z": 225
				},
				"scale3D":
				{
					"x": 1,
					"y": 1,
					"z": 1
				}
			},
			"assetPath": "SM_Cube_01"
		},
		{
			"transform":
			{
				"rotation":
				{
					"x": -0,
					"y": 0,
					"z": -0.38268366456031799,
					"w": 0.92387944459915161
				},
				"translation":
				{
					"x": -305,
					"y": 200,
					"z": 150
				},
				"scale3D":
				{
					"x": 1,
					"y": 1,
					"z": 1
				}
			},
			"assetPath": "SM_Cube_02"
		},
		{
			"transform":
			{
				"rotation":
				{
					"x": 0,
					"y": 0,
					"z": 0,
					"w": 1
				},
				"translation":
				{
					"x": -25,
					"y": 275,
					"z": 100
				},
				"scale3D":
				{
					"x": 1,
					"y": 1,
					"z": 1
				}
			},
			"assetPath": "SM_Cube_03"
		},
		{
			"transform":
			{
				"rotation":
				{
					"x": -0.7071068286895752,
					"y": -0,
					"z": 0,
					"w": 0.70710670948028564
				},
				"translation":
				{
					"x": 305,
					"y": -125,
					"z": 225
				},
				"scale3D":
				{
					"x": 1,
					"y": 1,
					"z": 1
				}
			},
			"assetPath": "SM_Cube_03"
		},
		{
			"transform":
			{
				"rotation":
				{
					"x": 0,
					"y": 0,
					"z": 0,
					"w": 1
				},
				"translation":
				{
					"x": 0,
					"y": 0,
					"z": 0
				},
				"scale3D":
				{
					"x": 1,
					"y": 1,
					"z": 1
				}
			},
			"assetPath": "SM_Room_01"
		},
		{
			"transform":
			{
				"rotation":
				{
					"x": 0,
					"y": 0,
					"z": 0,
					"w": 1
				},
				"translation":
				{
					"x": 60,
					"y": -300,
					"z": 140
				},
				"scale3D":
				{
					"x": 1,
					"y": 1,
					"z": 1
				}
			},
			"assetPath": "SM_Pyramid_01"
		},
		{
			"transform":
			{
				"rotation":
				{
					"x": -0,
					"y": 0,
					"z": -0.99619489908218384,
					"w": 0.087152779102325439
				},
				"translation":
				{
					"x": -50,
					"y": -30,
					"z": 0
				},
				"scale3D":
				{
					"x": 1,
					"y": 1,
					"z": 0.5
				}
			},
			"assetPath": "SM_MatPreviewMesh_01"
		},
		{
			"transform":
			{
				"rotation":
				{
					"x": -0,
					"y": 0,
					"z": -0.86602610349655151,
					"w": 0.49999880790710449
				},
				"translation":
				{
					"x": -610,
					"y": -30,
					"z": 0
				},
				"scale3D":
				{
					"x": 1,
					"y": 1,
					"z": 1.75
				}
			},
			"assetPath": "SM_MatPreviewMesh_01"
		},
		{
			"transform":
			{
				"rotation":
				{
					"x": 0,
					"y": -0,
					"z": 0.90630590915679932,
					"w": 0.42262226343154907
				},
				"translation":
				{
					"x": 630,
					"y": -30,
					"z": 0
				},
				"scale3D":
				{
					"x": 1,
					"y": 1,
					"z": 1.75
				}
			},
			"assetPath": "SM_MatPreviewMesh_01"
		}
	]
}